ecsh
