Metadata-Version: 1.0
Name: ecsh
Version: 0.2.1
Summary: Cli tool to access Amazon ECS containers with a shell
Home-page: https://github.com/apsl/ecsh
Author: Bartomeu Miro Mateu
Author-email: bmiro@apsl.net
License: GPLv3
Platform: UNKNOWN
